Metadata-Version: 2.1
Name: freecad-to-obj
Version: 0.1.0
Summary: Export FreeCAD models to the Wavefront (.obj) file format.
Home-page: https://github.com/gbroques/freecad-to-obj
Author: G Roques
License: UNKNOWN
Platform: UNKNOWN
Classifier: License :: OSI Approved :: GNU Lesser General Public License v2 or later (LGPLv2+)
Classifier: Programming Language :: Python :: 3 :: Only
